goblin/__init__.py
goblin/analyzer.py
goblin/ascii_logo.py
goblin/cli.py
goblin/config.py
goblin/detector.py
goblin/shame_o_meter.py
goblin/smell_types.py
goblin_cli-0.1.4.dist-info/licenses/LICENSE
goblin_cli-0.1.4.dist-info/METADATA
goblin_cli-0.1.4.dist-info/WHEEL
goblin_cli-0.1.4.dist-info/entry_points.txt
goblin_cli-0.1.4.dist-info/top_level.txt
goblin_cli-0.1.4.dist-info/RECORD
