Metadata-Version: 2.4
Name: goblin-cli
Version: 0.1.4
Summary: A CLI tool for automating and managing Java unit tests with enhanced reporting and debugging features (development version)
Author: gpapachr
Project-URL: Homepage, https://github.com/gpapachr/unit-test-goblin
Requires-Python: >=3.9
License-File: LICENSE
Requires-Dist: javalang==0.13.0
Requires-Dist: rich==14.0.0
Requires-Dist: toml~=0.10.2
Provides-Extra: dev
Requires-Dist: pytest==8.3.5; extra == "dev"
Requires-Dist: ruff==0.11.6; extra == "dev"
Requires-Dist: iniconfig==2.1.0; extra == "dev"
Requires-Dist: packaging==25.0; extra == "dev"
Requires-Dist: pluggy==1.5.0; extra == "dev"
Requires-Dist: six==1.17.0; extra == "dev"
Dynamic: license-file
